pytorchse3/__init__.py
pytorchse3/_modidx.py
pytorchse3/se3.py
pytorchse3/so3.py
pytorchse3/utils.py
pytorchse3-0.0.3.dist-info/LICENSE
pytorchse3-0.0.3.dist-info/METADATA
pytorchse3-0.0.3.dist-info/WHEEL
pytorchse3-0.0.3.dist-info/entry_points.txt
pytorchse3-0.0.3.dist-info/top_level.txt
pytorchse3-0.0.3.dist-info/RECORD
