Metadata-Version: 2.1
Name: pytorchse3
Version: 0.0.3
Summary: Numerically stable implementations of batched SE(3) exp and log maps
Home-page: https://github.com/eigenvivek/pytorchse3
Author: Vivek Gopalakrishnan
Author-email: vivekg@mit.edu
License: MIT License
Keywords: nbdev jupyter notebook python
Classifier: Development Status :: 4 - Beta
Classifier: Intended Audience :: Developers
Classifier: Natural Language :: English
Classifier: Programming Language :: Python :: 3.7
Classifier: Programming Language :: Python :: 3.8
Classifier: Programming Language :: Python :: 3.9
Classifier: Programming Language :: Python :: 3.10
Classifier: License :: OSI Approved :: MIT License
Requires-Python: >=3.7
License-File: LICENSE
Requires-Dist: torch
Provides-Extra: dev
Requires-Dist: black ; extra == 'dev'
